{
    "0": {
        "id": "robecard",
        "itemid": 300270,
        "label": "Garment Card",
        "equipname": "Empathizer Card",
        "effectlist": [
            {
                "EffectNumber": 10,
                "EffectType": {
                    "id": "RangedDamagePercent"
                },
                "Enable": true
            },
            {
                "EffectNumber": "-25",
                "EffectType": {
                    "id": "SPPercent"
                },
                "Enable": true
            }
        ],
        "combolist": [
            {
                "itemids": [4392],
                "equipname": "Dame of Sentinel Card",
                "effectlist": [
                    {
                        "EffectNumber": "BLV>199?(15*FLOOR(BDE/40)):0",
                        "EffectType": {
                            "id": "RangedDamagePercent"
                        },
                        "Enable": true
                    }
                ]
            }
        ],
        "idx": 3
    },
    "1": {
        "id": "robecard",
        "itemid": 300271,
        "label": "Garment Card",
        "equipname": "Happiness Giver Card",
        "effectlist": [
            {
                "EffectNumber": 10,
                "EffectType": {
                    "id": "MeleeDamagePercent"
                },
                "Enable": true
            },
            {
                "EffectNumber": "-25",
                "EffectType": {
                    "id": "SPPercent"
                },
                "Enable": true
            }
        ],
        "combolist": [
            {
                "itemids": [4393],
                "equipname": "Mistress of Shelter Card",
                "effectlist": [
                    {
                        "EffectNumber": "BLV>199?(15*FLOOR(BST/40)):0",
                        "EffectType": {
                            "id": "MeleeDamagePercent"
                        },
                        "Enable": true
                    }
                ]
            }
        ],
        "idx": 3
    }
}